README.md
pyproject.toml
setup.py
./build/lib/build/lib/build/lib/build/lib/build/lib/build/lib/build/lib/build/lib/build/lib/build/lib/src/__init__.py
./build/lib/build/lib/build/lib/build/lib/build/lib/build/lib/build/lib/build/lib/build/lib/build/lib/src/s3_lifecycle/__init__.py
./build/lib/build/lib/build/lib/build/lib/build/lib/build/lib/build/lib/build/lib/build/lib/build/lib/src/s3_lifecycle/cli.py
./build/lib/build/lib/build/lib/build/lib/build/lib/build/lib/build/lib/build/lib/build/lib/build/lib/src/s3_lifecycle/diff.py
./build/lib/build/lib/build/lib/build/lib/build/lib/build/lib/build/lib/build/lib/build/lib/build/lib/src/s3_lifecycle/exceptions.py
./build/lib/build/lib/build/lib/build/lib/build/lib/build/lib/build/lib/build/lib/build/lib/build/lib/src/s3_lifecycle/manager.py
./build/lib/build/lib/build/lib/build/lib/build/lib/build/lib/build/lib/build/lib/build/lib/build/lib/src/s3_lifecycle/policy.py
./build/lib/build/lib/build/lib/build/lib/build/lib/build/lib/build/lib/build/lib/build/lib/build/lib/src/s3_lifecycle/validators.py
./build/lib/build/lib/build/lib/build/lib/build/lib/build/lib/build/lib/build/lib/build/lib/build/lib/tests/__init__.py
./build/lib/build/lib/build/lib/build/lib/build/lib/build/lib/build/lib/build/lib/build/lib/build/lib/tests/test_diff.py
./build/lib/build/lib/build/lib/build/lib/build/lib/build/lib/build/lib/build/lib/build/lib/build/lib/tests/test_manager_mocked.py
./build/lib/build/lib/build/lib/build/lib/build/lib/build/lib/build/lib/build/lib/build/lib/build/lib/tests/test_policy_validation.py
./build/lib/build/lib/build/lib/build/lib/build/lib/build/lib/build/lib/build/lib/build/lib/src/__init__.py
./build/lib/build/lib/build/lib/build/lib/build/lib/build/lib/build/lib/build/lib/build/lib/src/s3_lifecycle/__init__.py
./build/lib/build/lib/build/lib/build/lib/build/lib/build/lib/build/lib/build/lib/build/lib/src/s3_lifecycle/cli.py
s3_lifecycle_delta.egg-info/PKG-INFO
s3_lifecycle_delta.egg-info/SOURCES.txt
s3_lifecycle_delta.egg-info/dependency_links.txt
s3_lifecycle_delta.egg-info/requires.txt
s3_lifecycle_delta.egg-info/top_level.txt
