Metadata-Version: 2.4
Name: s3-lifecycle-delta
Version: 0.1.0
Summary: A Python library to manage S3 lifecycle policies and track changes in Delta format.
Home-page: https://github.com/yourusername/your-library
Author: Fernando Oliveira Pereira
Author-email: Fernando Oliveira Pereira <oliveira-fernando1@hotmail.com>
License: MIT
Keywords: aws,s3,s3_lifecycle
Classifier: Programming Language :: Python :: 3
Classifier: License :: OSI Approved :: MIT License
Classifier: Operating System :: OS Independent
Requires-Python: >=3.6
Requires-Dist: pytest
Requires-Dist: moto
Requires-Dist: pydantic
Requires-Dist: boto3
Dynamic: author
Dynamic: home-page
Dynamic: requires-python
